zip_gui/__init__.py
zip_gui/app.py
zip_gui/style.py
zip_gui-1.0.1.dist-info/METADATA
zip_gui-1.0.1.dist-info/WHEEL
zip_gui-1.0.1.dist-info/entry_points.txt
zip_gui-1.0.1.dist-info/RECORD
