Metadata-Version: 2.3
Name: zip_gui
Version: 1.0.1
Summary: A clean and straightforward graphical interface for compressing (packing) and extracting (unpacking) archive files, built with Python and PySide6.
Project-URL: Homepage, https://github.com/twn39/zip-gui
Project-URL: Documentation, https://github.com/twn39/zip-gui
Project-URL: Repository, https://github.com/twn39/zip-gui
Project-URL: Source Code, https://github.com/twn39/zip-gui
Author-email: curry tang <twn39@163.com>
Maintainer-email: curry tang <twn39@163.com>
Keywords: GUI,compress,zip,zip gui
Classifier: Intended Audience :: Developers
Classifier: License :: OSI Approved :: MIT License
Classifier: Programming Language :: Python :: 3
Classifier: Programming Language :: Python :: 3.10
Classifier: Programming Language :: Python :: 3.11
Classifier: Programming Language :: Python :: 3.12
Requires-Python: >=3.10
Requires-Dist: pyside6>=6.9.0
Requires-Dist: qtawesome>=1.4.0
